cfmacro/__init__.py
cfmacro/cfmacro.py
cfmacro/_resources/examples/cf_snippet_sg.template
cfmacro/_resources/examples/lambda.py
cfmacro/_resources/examples/lambda_requirements.txt
cfmacro/_resources/examples/macro.template
cfmacro/cloudformation/__init__.py
cfmacro/cloudformation/elements.py
cfmacro/core/__init__.py
cfmacro/core/base.py
cfmacro/core/engine.py
cfmacro/core/template.py
cfmacro/processors/__init__.py
cfmacro/processors/sg_processor.py
cfmacro/utils/__init__.py
cfmacro/utils/package_lambda.py
cfmacro/utils/pprint.py
cfmacro-0.6.0.dist-info/AUTHORS.rst
cfmacro-0.6.0.dist-info/LICENSE
cfmacro-0.6.0.dist-info/METADATA
cfmacro-0.6.0.dist-info/WHEEL
cfmacro-0.6.0.dist-info/top_level.txt
cfmacro-0.6.0.dist-info/RECORD
