Metadata-Version: 2.1
Name: cfmacro
Version: 0.6.0
Summary: A CloudFormation Toolkit to   easily implement core for Macro
Home-page: https://github.com/gchiesa/cfmacro
Author: Giuseppe Chiesa
Author-email: mail@giuseppechiesa.it
License: MIT license
Keywords: cfmacro
Platform: UNKNOWN
Classifier: Development Status :: 2 - Pre-Alpha
Classifier: Intended Audience :: Developers
Classifier: License :: OSI Approved :: MIT License
Classifier: Natural Language :: English
Classifier: Programming Language :: Python :: 2
Classifier: Programming Language :: Python :: 2.7
Classifier: Programming Language :: Python :: 3
Classifier: Programming Language :: Python :: 3.4
Classifier: Programming Language :: Python :: 3.5
Classifier: Programming Language :: Python :: 3.6
Classifier: Programming Language :: Python :: 3.7
